oops_all_itertools/__init__.py
oops_all_itertools-3.3.3.dist-info/licenses/LICENSE
oops_all_itertools-3.3.3.dist-info/WHEEL
oops_all_itertools-3.3.3.dist-info/METADATA
oops_all_itertools-3.3.3.dist-info/RECORD
