Metadata-Version: 2.4
Name: oops-all-itertools
Version: 3.3.3
Summary: itertools and more-itertools all in one namespace
Keywords: itertools,iterator,iteration,filter,peek,peekable,chunk,chunked
Author: Lonnen
Classifier: Development Status :: 5 - Production/Stable
Classifier: Intended Audience :: Developers
Classifier: Natural Language :: English
Classifier: License :: OSI Approved :: MIT License
Classifier: Programming Language :: Python :: 3
Classifier: Programming Language :: Python :: 3.9
Classifier: Programming Language :: Python :: 3.10
Classifier: Programming Language :: Python :: 3.11
Classifier: Programming Language :: Python :: 3.12
Classifier: Programming Language :: Python :: 3.13
Classifier: Programming Language :: Python :: 3 :: Only
Classifier: Programming Language :: Python :: Implementation :: CPython
Classifier: Programming Language :: Python :: Implementation :: PyPy
Classifier: Topic :: Software Development :: Libraries
License-File: LICENSE
Requires-Dist: more-itertools == 10.7.0
Project-URL: Home, https://github.com/lonnen/oops-all-itertools
